{
  "version": 1,
  "year": 2023,
  "language": "ts",
  "days": [
    {
      "part1": {
        "solved": true,
        "result": "54927",
        "attempts": [],
        "time": 1.0505
      },
      "part2": {
        "solved": true,
        "result": "54581",
        "attempts": [],
        "time": 34.757542
      }
    },
    {
      "part1": {
        "solved": true,
        "result": "2679",
        "attempts": [],
        "time": 0.439791
      },
      "part2": {
        "solved": true,
        "result": "77607",
        "attempts": [],
        "time": 0.369208
      }
    },
    {
      "part1": {
        "solved": true,
        "result": "535351",
        "attempts": [],
        "time": 1.339709
      },
      "part2": {
        "solved": true,
        "result": "87287096",
        "attempts": [],
        "time": 15.053417
      }
    },
    {
      "part1": {
        "solved": true,
        "result": "26346",
        "attempts": [],
        "time": 2.163263
      },
      "part2": {
        "solved": true,
        "result": "8467762",
        "attempts": [],
        "time": 168.487711
      }
    },
    {
      "part1": {
        "solved": true,
        "result": "111627841",
        "attempts": [],
        "time": 0.5746
      },
      "part2": {
        "solved": true,
        "result": "69323688",
        "attempts": [
          "69323689"
        ],
        "time": 89467.289298
      }
    },
    {
      "part1": {
        "solved": true,
        "result": "1159152",
        "attempts": [],
        "time": 0.038451
      },
      "part2": {
        "solved": true,
        "result": "41513103",
        "attempts": [],
        "time": 156.43195
      }
    },
    {
      "part1": {
        "solved": true,
        "result": "248812215",
        "attempts": [],
        "time": 4.55945
      },
      "part2": {
        "solved": true,
        "result": "250057090",
        "attempts": [
          "249924564",
          "250310811"
        ],
        "time": 7.840195
      }
    },
    {
      "part1": {
        "solved": false,
        "result": null,
        "attempts": [],
        "time": null
      },
      "part2": {
        "solved": false,
        "result": null,
        "attempts": [],
        "time": null
      }
    },
    {
      "part1": {
        "solved": false,
        "result": null,
        "attempts": [],
        "time": null
      },
      "part2": {
        "solved": false,
        "result": null,
        "attempts": [],
        "time": null
      }
    },
    {
      "part1": {
        "solved": false,
        "result": null,
        "attempts": [],
        "time": null
      },
      "part2": {
        "solved": false,
        "result": null,
        "attempts": [],
        "time": null
      }
    },
    {
      "part1": {
        "solved": false,
        "result": null,
        "attempts": [],
        "time": null
      },
      "part2": {
        "solved": false,
        "result": null,
        "attempts": [],
        "time": null
      }
    },
    {
      "part1": {
        "solved": false,
        "result": null,
        "attempts": [],
        "time": null
      },
      "part2": {
        "solved": false,
        "result": null,
        "attempts": [],
        "time": null
      }
    },
    {
      "part1": {
        "solved": false,
        "result": null,
        "attempts": [],
        "time": null
      },
      "part2": {
        "solved": false,
        "result": null,
        "attempts": [],
        "time": null
      }
    },
    {
      "part1": {
        "solved": false,
        "result": null,
        "attempts": [],
        "time": null
      },
      "part2": {
        "solved": false,
        "result": null,
        "attempts": [],
        "time": null
      }
    },
    {
      "part1": {
        "solved": false,
        "result": null,
        "attempts": [],
        "time": null
      },
      "part2": {
        "solved": false,
        "result": null,
        "attempts": [],
        "time": null
      }
    },
    {
      "part1": {
        "solved": false,
        "result": null,
        "attempts": [],
        "time": null
      },
      "part2": {
        "solved": false,
        "result": null,
        "attempts": [],
        "time": null
      }
    },
    {
      "part1": {
        "solved": false,
        "result": null,
        "attempts": [],
        "time": null
      },
      "part2": {
        "solved": false,
        "result": null,
        "attempts": [],
        "time": null
      }
    },
    {
      "part1": {
        "solved": false,
        "result": null,
        "attempts": [],
        "time": null
      },
      "part2": {
        "solved": false,
        "result": null,
        "attempts": [],
        "time": null
      }
    },
    {
      "part1": {
        "solved": false,
        "result": null,
        "attempts": [],
        "time": null
      },
      "part2": {
        "solved": false,
        "result": null,
        "attempts": [],
        "time": null
      }
    },
    {
      "part1": {
        "solved": false,
        "result": null,
        "attempts": [],
        "time": null
      },
      "part2": {
        "solved": false,
        "result": null,
        "attempts": [],
        "time": null
      }
    },
    {
      "part1": {
        "solved": false,
        "result": null,
        "attempts": [],
        "time": null
      },
      "part2": {
        "solved": false,
        "result": null,
        "attempts": [],
        "time": null
      }
    },
    {
      "part1": {
        "solved": false,
        "result": null,
        "attempts": [],
        "time": null
      },
      "part2": {
        "solved": false,
        "result": null,
        "attempts": [],
        "time": null
      }
    },
    {
      "part1": {
        "solved": false,
        "result": null,
        "attempts": [],
        "time": null
      },
      "part2": {
        "solved": false,
        "result": null,
        "attempts": [],
        "time": null
      }
    },
    {
      "part1": {
        "solved": false,
        "result": null,
        "attempts": [],
        "time": null
      },
      "part2": {
        "solved": false,
        "result": null,
        "attempts": [],
        "time": null
      }
    },
    {
      "part1": {
        "solved": false,
        "result": null,
        "attempts": [],
        "time": null
      },
      "part2": {
        "solved": false,
        "result": null,
        "attempts": [],
        "time": null
      }
    }
  ]
}